sapperchain/__init__.py
sapperchain/tool.py
sapperchain/agent/__init__.py
sapperchain/agent/agent_property.py
sapperchain/function_module/__init__.py
sapperchain/function_module/agent_executor.py
sapperchain/function_module/memory_manager.py
sapperchain/function_module/rag_handler.py
sapperchain/server/__init__.py
sapperchain/server/run_chain.py
sapperchain-0.0.2.dist-info/LICENSE
sapperchain-0.0.2.dist-info/METADATA
sapperchain-0.0.2.dist-info/WHEEL
sapperchain-0.0.2.dist-info/top_level.txt
sapperchain-0.0.2.dist-info/RECORD
