Metadata-Version: 2.1
Name: sapperchain
Version: 0.0.2
Summary: Programming for natural language
Home-page: https://github.com/promptsapper/sapperchain
Author: ChengYu && Yishun Wu
Author-email: author@example.com
Classifier: Programming Language :: Python :: 3
Classifier: License :: OSI Approved :: MIT License
Classifier: Operating System :: OS Independent
License-File: LICENSE
